docs/__init__.py
docs/conf.py
docs/api/__init__.py
ed_win/__init__.py
ed_win/c_mst.py
ed_win/c_mst_cables.py
ed_win/collection_system.py
ed_win/intersection_checker.py
ed_win/two_lines_intersecting.py
ed_win/wind_farm_network.py
ed_win/tests/__init__.py
ed_win/tests/test_wind_farm_network.py
ed_win-0.0.1.dist-info/LICENSE
ed_win-0.0.1.dist-info/METADATA
ed_win-0.0.1.dist-info/WHEEL
ed_win-0.0.1.dist-info/top_level.txt
ed_win-0.0.1.dist-info/zip-safe
ed_win-0.0.1.dist-info/RECORD
