Metadata-Version: 2.1
Name: ed-win
Version: 0.0.1
Summary: EDWIN an optimization and design package for electrical networks in windfarms
Home-page: https://gitlab.windenergy.dtu.dk/TOPFARM/EDWIN
Author: DTU Wind Energy
Author-email: juru@dtu.dk
License: MIT
Platform: UNKNOWN
License-File: LICENSE
Requires-Dist: matplotlib
Requires-Dist: numpy
Requires-Dist: xarray
Requires-Dist: scipy
